diffuse/base_forward_model.py
diffuse/predictor.py
diffuse/.ipynb_checkpoints/conditional-checkpoint.py
diffuse/.ipynb_checkpoints/data_loader-checkpoint.py
diffuse/.ipynb_checkpoints/score_matching-checkpoint.py
diffuse/.ipynb_checkpoints/sde-checkpoint.py
diffuse/denoisers/__init__.py
diffuse/denoisers/base.py
diffuse/denoisers/denoiser.py
diffuse/denoisers/pnp_denoiser.py
diffuse/denoisers/utils.py
diffuse/denoisers/cond/__init__.py
diffuse/denoisers/cond/base.py
diffuse/denoisers/cond/dps.py
diffuse/denoisers/cond/fps.py
diffuse/denoisers/cond/tmp.py
diffuse/denoisers/cond/tmp2.py
diffuse/denoisers/cond/tmp3.py
diffuse/diffusion/__init__.py
diffuse/diffusion/sde.py
diffuse/examples/gaussian_mixtures/cond_mixture.py
diffuse/examples/gaussian_mixtures/initialization.py
diffuse/examples/gaussian_mixtures/mixture.py
diffuse/examples/gaussian_mixtures/mixture_evolution.py
diffuse/examples/gaussian_mixtures/plotting.py
diffuse/examples/gaussian_mixtures/forward_models/matrix_product.py
diffuse/examples/mnist/forward_model.py
diffuse/integrator/__init__.py
diffuse/integrator/base.py
diffuse/integrator/deterministic.py
diffuse/integrator/stochastic.py
diffuse/neural_network/__init__.py
diffuse/neural_network/blocks/__init__.py
diffuse/neural_network/blocks/attention.py
diffuse/neural_network/blocks/decoder.py
diffuse/neural_network/blocks/downsample.py
diffuse/neural_network/blocks/encoder.py
diffuse/neural_network/blocks/resnet_block.py
diffuse/neural_network/blocks/time_embedding.py
diffuse/neural_network/blocks/timestep.py
diffuse/neural_network/blocks/upsample.py
diffuse/neural_network/nn/__init__.py
diffuse/neural_network/nn/condUNet.py
diffuse/neural_network/nn/params.py
diffuse/neural_network/nn/sdVae.py
diffuse/timer/__init__.py
diffuse/timer/base.py
diffuse/utils/__init__.py
diffuse/utils/logger.py
diffuse/utils/mapping.py
diffuse_jax-0.1.0.dist-info/licenses/LICENSE
diffuse_jax-0.1.0.dist-info/METADATA
diffuse_jax-0.1.0.dist-info/WHEEL
diffuse_jax-0.1.0.dist-info/top_level.txt
diffuse_jax-0.1.0.dist-info/RECORD
