Metadata-Version: 2.4
Name: diffuse-jax
Version: 0.1.0
Summary: A research-oriented package for diffusion-based generative modeling with modular components
Author-email: Jacopo Iollo <jacopo.iollo@inria.fr>
License: Apache-2.0
Project-URL: Homepage, https://github.com/jcopo/diffuse
Project-URL: Repository, https://github.com/jcopo/diffuse
Project-URL: Documentation, https://diffuse.readthedocs.io
Project-URL: Bug Tracker, https://github.com/jcopo/diffuse/issues
Keywords: diffusion,generative-models,machine-learning,jax,research
Classifier: Development Status :: 3 - Alpha
Classifier: Intended Audience :: Science/Research
Classifier: License :: OSI Approved :: Apache Software License
Classifier: Operating System :: OS Independent
Classifier: Programming Language :: Python :: 3
Classifier: Programming Language :: Python :: 3.10
Classifier: Programming Language :: Python :: 3.11
Classifier: Programming Language :: Python :: 3.12
Classifier: Topic :: Scientific/Engineering :: Artificial Intelligence
Requires-Python: >=3.6
License-File: LICENSE
Requires-Dist: jax>=0.4.31
Requires-Dist: jaxlib>=0.4.31
Requires-Dist: optax>=0.2.2
Requires-Dist: matplotlib>=3.8.2
Requires-Dist: numpy>=1.24.0
Requires-Dist: einops>=0.8.0
Requires-Dist: tqdm>=4.66.1
Requires-Dist: jax-tqdm>=0.1.2
Requires-Dist: flax>=0.8.5
Requires-Dist: chex>=0.1.86
Requires-Dist: jaxtyping>=0.2.24
Provides-Extra: dev
Requires-Dist: pytest>=6.0; extra == "dev"
Requires-Dist: pytest-cov; extra == "dev"
Provides-Extra: docs
Requires-Dist: sphinx; extra == "docs"
Requires-Dist: sphinx-rtd-theme; extra == "docs"
Dynamic: license-file
Dynamic: requires-python
